{
	"easycom": {
		"^u-(.*)": "uview-ui/components/u-$1/u-$1.vue"
	},
	"pages": [ //pages数组中第一项表示应用启动页，参考：https://uniapp.dcloud.io/collocation/pages
		{
			"path": "pages/index/index",
			"style": {
				"navigationBarTitleText": "首页"
			}
		}
	    ,{
            "path" : "pages/profile/profile",
            "style" :                                                                                    
            {
                "navigationBarTitleText": "个人中心",
                "enablePullDownRefresh": false
            }
            
        }
        ,{
            "path" : "pages/new/new",
            "style" :                                                                                    
            {
                "navigationBarTitleText": "新增",
                "enablePullDownRefresh": false
            }
            
        }
    ],
	"globalStyle": {
		"navigationBarTextStyle": "black",
		"navigationBarTitleText": "uni-app",
		"navigationBarBackgroundColor": "#F8F8F8",
		"backgroundColor": "#F8F8F8"
	},
	"tabBar": {
		"borderStyle": "black",
		"backgroundColor": "#333",
		"color": "#8F8F94",
		"selectedColor": "#f33e54",
		"list": [{
				"pagePath": "pages/index/index",
				"iconPath": "static/img/tabbar/home.png",
				"selectedIconPath": "static/img/tabbar/homeactive.png",
				"text": "首页"
			},
			//#ifdef MP-WEIXIN
			{
				"pagePath": "pages/new/new",
				"iconPath": "static/img/tabbar/add.png",
				"selectedIconPath": "static/img/tabbar/addactive.png",
				"text": "发布"
			},
			//#endif
			//#ifndef MP-WEIXIN
			{
				"pagePath": "pages/new/new",
				"iconPath": "static/img/tabbar/add.png",
				"selectedIconPath": "static/img/tabbar/addactive.png"
			},
			//#endif
			{
				"pagePath": "pages/profile/profile",
				"iconPath": "static/img/tabbar/me.png",
				"selectedIconPath": "static/img/tabbar/meactive.png",
				"text": "我"
			}
		]
	}
}
